ranium_reader/__init__.py
ranium_reader/slack.py
ranium_reader-1.0.3.dist-info/LICENSE
ranium_reader-1.0.3.dist-info/WHEEL
ranium_reader-1.0.3.dist-info/METADATA
ranium_reader-1.0.3.dist-info/RECORD
