Metadata-Version: 2.1
Name: ranium_reader
Version: 1.0.3
Summary: sample package of ranium
Home-page: UNKNOWN
License: UNKNOWN
Author: Dhananjay
Author-email: dhananjay@ranium.in
Classifier: License :: OSI Approved :: MIT License
